{"nodes": [{"name": "trans", "index": 0}, {"name": "trans people", "index": 1}, {"name": "transgender", "index": 2}, {"name": "gender", "index": 3}, {"name": "genderfluid", "index": 4}, {"name": "femboy", "index": 5}, {"name": "present", "index": 6}, {"name": "testosterone", "index": 7}, {"name": "cis", "index": 8}, {"name": "trans*", "index": 9}, {"name": "trans woman", "index": 10}, {"name": "transgirl", "index": 11}, {"name": "dysphoria", "index": 12}, {"name": "non-binary", "index": 13}, {"name": "#tgirl", "index": 14}, {"name": "cissexism", "index": 15}, {"name": "shemale", "index": 16}, {"name": "sissy", "index": 17}, {"name": "tranny", "index": 18}, {"name": "transgendered", "index": 19}, {"name": "binder", "index": 20}, {"name": "post-op", "index": 21}, {"name": "transsexual", "index": 22}, {"name": "transphobia", "index": 23}, {"name": "misgender", "index": 24}, {"name": "transpeople", "index": 25}, {"name": "transmisogyny", "index": 26}, {"name": "hormone replacement therapy", "index": 27}, {"name": "gender reassignment", "index": 28}, {"name": "gender non-conforming", "index": 29}, {"name": "gender binary", "index": 30}, {"name": "voice", "index": 31}, {"name": "amab", "index": 32}, {"name": "preferred pronoun", "index": 33}, {"name": "estrogen", "index": 34}, {"name": "transwoman", "index": 35}], "links": [{"source": 0, "weight": 0.8571428571428572, "target": 1}, {"source": 0, "weight": 0.8571428571428572, "target": 2}, {"source": 1, "weight": 0.8571428571428572, "target": 2}, {"source": 3, "weight": 0.8571428571428572, "target": 2}, {"source": 0, "weight": 4.428571428571429, "target": 1}, {"source": 3, "weight": 0.5, "target": 4}, {"source": 5, "weight": 0.5, "target": 6}, {"source": 7, "weight": 5.5, "target": 0}, {"source": 8, "weight": 0.5, "target": 4}, {"source": 9, "weight": 0.8571428571428572, "target": 2}, {"source": 7, "weight": 0.8571428571428572, "target": 0}, {"source": 7, "weight": 0.8571428571428572, "target": 10}, {"source": 0, "weight": 0.8571428571428572, "target": 10}, {"source": 0, "weight": 0.8571428571428572, "target": 11}, {"source": 8, "weight": 0.5, "target": 12}, {"source": 3, "weight": 0.5, "target": 13}, {"source": 14, "weight": 0.5, "target": 3}, {"source": 13, "weight": 0.5, "target": 9}, {"source": 6, "weight": 0.5, "target": 2}, {"source": 13, "weight": 1.9285714285714288, "target": 7}, {"source": 15, "weight": 0.5, "target": 0}, {"source": 14, "weight": 0.5, "target": 16}, {"source": 14, "weight": 0.5, "target": 17}, {"source": 14, "weight": 0.5, "target": 18}, {"source": 16, "weight": 0.5, "target": 17}, {"source": 16, "weight": 0.5, "target": 18}, {"source": 17, "weight": 0.5, "target": 18}, {"source": 8, "weight": 0.5, "target": 3}, {"source": 8, "weight": 0.5, "target": 0}, {"source": 8, "weight": 0.5, "target": 1}, {"source": 3, "weight": 0.5, "target": 0}, {"source": 3, "weight": 0.5, "target": 1}, {"source": 0, "weight": 0.5, "target": 1}, {"source": 14, "weight": 2.2857142857142856, "target": 17}, {"source": 7, "weight": 0.5, "target": 19}, {"source": 20, "weight": 0.8571428571428572, "target": 21}, {"source": 5, "weight": 0.5, "target": 7}, {"source": 18, "weight": 0.5, "target": 22}, {"source": 21, "weight": 2.2857142857142856, "target": 7}, {"source": 7, "weight": 0.8571428571428572, "target": 0}, {"source": 7, "weight": 0.8571428571428572, "target": 23}, {"source": 0, "weight": 0.8571428571428572, "target": 23}, {"source": 8, "weight": 0.5, "target": 7}, {"source": 8, "weight": 0.5, "target": 0}, {"source": 8, "weight": 0.5, "target": 1}, {"source": 7, "weight": 0.5, "target": 0}, {"source": 7, "weight": 0.5, "target": 1}, {"source": 0, "weight": 0.5, "target": 1}, {"source": 24, "weight": 0.5, "target": 7}, {"source": 3, "weight": 0.5, "target": 0}, {"source": 3, "weight": 0.5, "target": 1}, {"source": 0, "weight": 0.5, "target": 1}, {"source": 7, "weight": 0.5, "target": 0}, {"source": 7, "weight": 0.5, "target": 25}, {"source": 0, "weight": 0.5, "target": 25}, {"source": 8, "weight": 2.2857142857142856, "target": 7}, {"source": 0, "weight": 0.5, "target": 26}, {"source": 27, "weight": 0.5, "target": 7}, {"source": 12, "weight": 0.5, "target": 2}, {"source": 8, "weight": 1.9285714285714288, "target": 0}, {"source": 3, "weight": 0.5, "target": 28}, {"source": 8, "weight": 0.5, "target": 18}, {"source": 29, "weight": 0.8571428571428572, "target": 7}, {"source": 3, "weight": 1.9285714285714288, "target": 30}, {"source": 19, "weight": 0.5, "target": 31}, {"source": 7, "weight": 2.2857142857142856, "target": 23}, {"source": 0, "weight": 1.9285714285714288, "target": 2}, {"source": 8, "weight": 0.5, "target": 0}, {"source": 8, "weight": 0.5, "target": 10}, {"source": 0, "weight": 0.5, "target": 10}, {"source": 7, "weight": 1.9285714285714288, "target": 2}, {"source": 32, "weight": 0.5, "target": 8}, {"source": 32, "weight": 0.5, "target": 0}, {"source": 8, "weight": 0.5, "target": 0}, {"source": 33, "weight": 0.5, "target": 7}, {"source": 16, "weight": 0.5, "target": 22}, {"source": 7, "weight": 1.5714285714285716, "target": 22}, {"source": 0, "weight": 3.0000000000000004, "target": 10}, {"source": 34, "weight": 0.5, "target": 27}, {"source": 8, "weight": 0.5, "target": 13}, {"source": 8, "weight": 0.5, "target": 0}, {"source": 13, "weight": 0.5, "target": 0}, {"source": 13, "weight": 0.5, "target": 0}, {"source": 5, "weight": 1.9285714285714288, "target": 17}, {"source": 3, "weight": 0.5, "target": 7}, {"source": 3, "weight": 0.5, "target": 0}, {"source": 3, "weight": 0.5, "target": 1}, {"source": 7, "weight": 0.5, "target": 0}, {"source": 7, "weight": 0.5, "target": 1}, {"source": 0, "weight": 0.5, "target": 1}, {"source": 8, "weight": 0.5, "target": 7}, {"source": 8, "weight": 0.5, "target": 35}, {"source": 7, "weight": 0.5, "target": 35}, {"source": 8, "weight": 0.5, "target": 7}, {"source": 8, "weight": 0.5, "target": 23}, {"source": 7, "weight": 0.5, "target": 23}, {"source": 8, "weight": 0.5, "target": 0}, {"source": 8, "weight": 0.5, "target": 1}, {"source": 0, "weight": 0.5, "target": 1}, {"source": 0, "weight": 0.5, "target": 25}, {"source": 14, "weight": 4.428571428571429, "target": 16}]}