{"links": [{"weight": 0.5, "target": 1, "source": 0}, {"weight": 0.5, "target": 3, "source": 2}, {"weight": 0.5, "target": 4, "source": 2}, {"weight": 0.5, "target": 4, "source": 3}, {"weight": 0.5, "target": 5, "source": 3}, {"weight": 0.5, "target": 6, "source": 2}, {"weight": 5.5, "target": 3, "source": 2}], "nodes": [{"index": 0, "name": "cis"}, {"index": 1, "name": "genderfluid"}, {"index": 2, "name": "testosterone"}, {"index": 3, "name": "trans"}, {"index": 4, "name": "trans people"}, {"index": 5, "name": "trans-man"}, {"index": 6, "name": "transgender"}]}