{"links": [{"target": 1, "source": 0, "weight": 0.5}, {"target": 2, "source": 0, "weight": 0.5}, {"target": 2, "source": 1, "weight": 0.5}, {"target": 4, "source": 3, "weight": 0.5}, {"target": 5, "source": 3, "weight": 0.5}, {"target": 5, "source": 4, "weight": 0.5}, {"target": 6, "source": 4, "weight": 0.5625}, {"target": 1, "source": 7, "weight": 0.5}, {"target": 8, "source": 7, "weight": 0.5}, {"target": 8, "source": 1, "weight": 0.5}, {"target": 1, "source": 9, "weight": 0.625}, {"target": 8, "source": 4, "weight": 0.5625}, {"target": 11, "source": 10, "weight": 0.5}, {"target": 2, "source": 1, "weight": 0.5625}, {"target": 5, "source": 1, "weight": 0.5625}, {"target": 5, "source": 2, "weight": 0.5625}, {"target": 5, "source": 4, "weight": 0.5}, {"target": 1, "source": 12, "weight": 0.5}, {"target": 13, "source": 12, "weight": 0.5}, {"target": 13, "source": 1, "weight": 0.5}, {"target": 1, "source": 11, "weight": 0.5}, {"target": 14, "source": 11, "weight": 0.5}, {"target": 14, "source": 1, "weight": 0.5}, {"target": 1, "source": 10, "weight": 0.5}, {"target": 5, "source": 10, "weight": 0.5}, {"target": 5, "source": 1, "weight": 0.5}, {"target": 13, "source": 1, "weight": 3.5}, {"target": 1, "source": 10, "weight": 0.5625}, {"target": 15, "source": 10, "weight": 0.5625}, {"target": 15, "source": 1, "weight": 0.5625}, {"target": 16, "source": 4, "weight": 0.6875}, {"target": 4, "source": 3, "weight": 0.5}, {"target": 5, "source": 8, "weight": 0.5}, {"target": 5, "source": 12, "weight": 0.5}, {"target": 6, "source": 17, "weight": 0.5}, {"target": 18, "source": 17, "weight": 0.5}, {"target": 18, "source": 6, "weight": 0.5}, {"target": 13, "source": 1, "weight": 0.75}, {"target": 8, "source": 1, "weight": 0.75}, {"target": 8, "source": 13, "weight": 0.75}, {"target": 19, "source": 18, "weight": 0.5}, {"target": 12, "source": 11, "weight": 0.5}, {"target": 20, "source": 18, "weight": 0.5}, {"target": 4, "source": 10, "weight": 0.5625}, {"target": 5, "source": 10, "weight": 0.5625}, {"target": 6, "source": 21, "weight": 1.1875}, {"target": 22, "source": 10, "weight": 0.5}, {"target": 1, "source": 7, "weight": 0.625}, {"target": 2, "source": 7, "weight": 0.625}, {"target": 2, "source": 1, "weight": 0.625}, {"target": 18, "source": 23, "weight": 0.5}, {"target": 25, "source": 24, "weight": 0.5}, {"target": 12, "source": 24, "weight": 0.5}, {"target": 12, "source": 25, "weight": 0.5}, {"target": 7, "source": 26, "weight": 0.5}, {"target": 1, "source": 26, "weight": 0.5}, {"target": 2, "source": 26, "weight": 0.5}, {"target": 1, "source": 7, "weight": 0.5}, {"target": 2, "source": 7, "weight": 0.5}, {"target": 2, "source": 1, "weight": 0.5}, {"target": 11, "source": 24, "weight": 0.875}, {"target": 12, "source": 24, "weight": 0.875}, {"target": 12, "source": 11, "weight": 0.875}, {"target": 6, "source": 4, "weight": 0.5}, {"target": 1, "source": 4, "weight": 0.5}, {"target": 1, "source": 6, "weight": 0.5}, {"target": 12, "source": 24, "weight": 0.6875}, {"target": 27, "source": 1, "weight": 0.5}, {"target": 18, "source": 28, "weight": 0.5}, {"target": 18, "source": 1, "weight": 1.0}, {"target": 2, "source": 1, "weight": 5.5}, {"target": 29, "source": 1, "weight": 0.625}, {"target": 7, "source": 30, "weight": 0.5}, {"target": 1, "source": 30, "weight": 0.5}, {"target": 2, "source": 30, "weight": 0.5}, {"target": 1, "source": 7, "weight": 0.5}, {"target": 2, "source": 7, "weight": 0.5}, {"target": 2, "source": 1, "weight": 0.5}, {"target": 1, "source": 31, "weight": 0.5}, {"target": 2, "source": 31, "weight": 0.5}, {"target": 2, "source": 1, "weight": 0.5}, {"target": 1, "source": 10, "weight": 0.5}, {"target": 2, "source": 10, "weight": 0.5}, {"target": 18, "source": 10, "weight": 0.5}, {"target": 2, "source": 1, "weight": 0.5}, {"target": 18, "source": 1, "weight": 0.5}, {"target": 18, "source": 2, "weight": 0.5}, {"target": 32, "source": 1, "weight": 0.5625}, {"target": 33, "source": 1, "weight": 0.5}, {"target": 1, "source": 34, "weight": 0.5}, {"target": 1, "source": 35, "weight": 0.5}, {"target": 2, "source": 35, "weight": 0.5}, {"target": 2, "source": 1, "weight": 0.5}, {"target": 5, "source": 1, "weight": 0.625}, {"target": 36, "source": 18, "weight": 0.5}, {"target": 20, "source": 8, "weight": 0.5}, {"target": 4, "source": 10, "weight": 0.5}, {"target": 16, "source": 10, "weight": 0.5}, {"target": 16, "source": 4, "weight": 0.5}, {"target": 37, "source": 3, "weight": 0.5}, {"target": 2, "source": 1, "weight": 0.5}, {"target": 18, "source": 1, "weight": 0.5}, {"target": 18, "source": 2, "weight": 0.5}, {"target": 7, "source": 4, "weight": 0.5}, {"target": 1, "source": 4, "weight": 0.5}, {"target": 1, "source": 7, "weight": 0.5}, {"target": 30, "source": 26, "weight": 0.5}, {"target": 15, "source": 1, "weight": 0.5625}, {"target": 39, "source": 38, "weight": 0.5}, {"target": 1, "source": 11, "weight": 0.5625}, {"target": 2, "source": 11, "weight": 0.5625}, {"target": 2, "source": 1, "weight": 0.5625}, {"target": 18, "source": 4, "weight": 0.75}, {"target": 20, "source": 1, "weight": 0.5}, {"target": 4, "source": 17, "weight": 0.5}, {"target": 1, "source": 17, "weight": 0.5}, {"target": 1, "source": 4, "weight": 0.5}, {"target": 1, "source": 7, "weight": 1.0}, {"target": 1, "source": 10, "weight": 1.5}, {"target": 2, "source": 10, "weight": 1.5}, {"target": 2, "source": 1, "weight": 1.5}, {"target": 8, "source": 1, "weight": 1.5}, {"target": 14, "source": 1, "weight": 0.6875}, {"target": 7, "source": 6, "weight": 0.5}, {"target": 4, "source": 17, "weight": 0.5}, {"target": 40, "source": 4, "weight": 0.625}, {"target": 18, "source": 9, "weight": 0.5}, {"target": 7, "source": 10, "weight": 0.5}, {"target": 1, "source": 10, "weight": 0.5}, {"target": 2, "source": 10, "weight": 0.5}, {"target": 1, "source": 7, "weight": 0.5}, {"target": 2, "source": 7, "weight": 0.5}, {"target": 2, "source": 1, "weight": 0.5}, {"target": 37, "source": 1, "weight": 0.5}, {"target": 18, "source": 24, "weight": 0.5}, {"target": 1, "source": 10, "weight": 0.5}, {"target": 8, "source": 10, "weight": 0.5}, {"target": 8, "source": 1, "weight": 0.5}, {"target": 41, "source": 1, "weight": 0.5}, {"target": 18, "source": 1, "weight": 0.5}, {"target": 18, "source": 41, "weight": 0.5}, {"target": 1, "source": 10, "weight": 0.5}, {"target": 2, "source": 10, "weight": 0.5}, {"target": 42, "source": 10, "weight": 0.5}, {"target": 2, "source": 1, "weight": 0.5}, {"target": 42, "source": 1, "weight": 0.5}, {"target": 42, "source": 2, "weight": 0.5}, {"target": 4, "source": 10, "weight": 0.5625}, {"target": 1, "source": 10, "weight": 0.5625}, {"target": 1, "source": 4, "weight": 0.5625}, {"target": 1, "source": 0, "weight": 0.5}, {"target": 18, "source": 12, "weight": 0.5}, {"target": 1, "source": 24, "weight": 0.5}, {"target": 43, "source": 4, "weight": 0.625}, {"target": 7, "source": 44, "weight": 0.5}, {"target": 1, "source": 6, "weight": 0.5}, {"target": 1, "source": 4, "weight": 1.1875}, {"target": 1, "source": 10, "weight": 1.8125}, {"target": 12, "source": 38, "weight": 0.5}, {"target": 42, "source": 1, "weight": 0.6875}, {"target": 4, "source": 10, "weight": 0.5}, {"target": 45, "source": 10, "weight": 0.5}, {"target": 1, "source": 10, "weight": 0.5}, {"target": 2, "source": 10, "weight": 0.5}, {"target": 45, "source": 4, "weight": 0.5}, {"target": 1, "source": 4, "weight": 0.5}, {"target": 2, "source": 4, "weight": 0.5}, {"target": 1, "source": 45, "weight": 0.5}, {"target": 2, "source": 45, "weight": 0.5}, {"target": 2, "source": 1, "weight": 0.5}, {"target": 8, "source": 1, "weight": 0.5}, {"target": 15, "source": 1, "weight": 0.5}, {"target": 15, "source": 8, "weight": 0.5}, {"target": 2, "source": 1, "weight": 0.5625}, {"target": 8, "source": 1, "weight": 0.5625}, {"target": 8, "source": 2, "weight": 0.5625}, {"target": 1, "source": 46, "weight": 0.5}, {"target": 45, "source": 3, "weight": 0.5}, {"target": 1, "source": 3, "weight": 0.5}, {"target": 1, "source": 45, "weight": 0.5}, {"target": 13, "source": 1, "weight": 0.5}, {"target": 14, "source": 1, "weight": 0.5}, {"target": 14, "source": 13, "weight": 0.5}, {"target": 15, "source": 8, "weight": 0.5}, {"target": 1, "source": 4, "weight": 0.6875}, {"target": 2, "source": 4, "weight": 0.6875}, {"target": 2, "source": 1, "weight": 0.6875}, {"target": 1, "source": 10, "weight": 0.5}, {"target": 41, "source": 10, "weight": 0.5}, {"target": 41, "source": 1, "weight": 0.5}, {"target": 11, "source": 24, "weight": 0.5625}, {"target": 16, "source": 4, "weight": 0.5}, {"target": 47, "source": 4, "weight": 0.5}, {"target": 47, "source": 16, "weight": 0.5}, {"target": 48, "source": 4, "weight": 0.5}, {"target": 1, "source": 10, "weight": 0.5}, {"target": 18, "source": 10, "weight": 0.5}, {"target": 18, "source": 1, "weight": 0.5}, {"target": 1, "source": 17, "weight": 0.5}, {"target": 2, "source": 17, "weight": 0.5}, {"target": 2, "source": 1, "weight": 0.5}, {"target": 16, "source": 4, "weight": 0.5}, {"target": 21, "source": 4, "weight": 0.5}, {"target": 7, "source": 4, "weight": 0.5}, {"target": 21, "source": 16, "weight": 0.5}, {"target": 7, "source": 16, "weight": 0.5}, {"target": 7, "source": 21, "weight": 0.5}, {"target": 49, "source": 5, "weight": 0.5625}, {"target": 27, "source": 28, "weight": 0.5}, {"target": 18, "source": 28, "weight": 0.5}, {"target": 33, "source": 28, "weight": 0.5}, {"target": 18, "source": 27, "weight": 0.5}, {"target": 33, "source": 27, "weight": 0.5}, {"target": 33, "source": 18, "weight": 0.5}, {"target": 41, "source": 1, "weight": 1.125}, {"target": 8, "source": 1, "weight": 0.5}, {"target": 18, "source": 1, "weight": 0.5}, {"target": 18, "source": 8, "weight": 0.5}, {"target": 5, "source": 37, "weight": 0.625}, {"target": 8, "source": 29, "weight": 0.5}, {"target": 5, "source": 15, "weight": 0.5}, {"target": 18, "source": 17, "weight": 0.5}, {"target": 1, "source": 10, "weight": 0.5}, {"target": 50, "source": 10, "weight": 0.5}, {"target": 50, "source": 1, "weight": 0.5}, {"target": 1, "source": 10, "weight": 0.8125}, {"target": 13, "source": 10, "weight": 0.8125}, {"target": 13, "source": 1, "weight": 0.8125}], "nodes": [{"index": 0, "name": "binder"}, {"index": 1, "name": "trans"}, {"index": 2, "name": "trans people"}, {"index": 3, "name": "cissexism"}, {"index": 4, "name": "gender"}, {"index": 5, "name": "transphobia"}, {"index": 6, "name": "genderqueer"}, {"index": 7, "name": "non-binary"}, {"index": 8, "name": "trans woman of color"}, {"index": 9, "name": "testosterone"}, {"index": 10, "name": "cis"}, {"index": 11, "name": "shemale"}, {"index": 12, "name": "tranny"}, {"index": 13, "name": "trans woman"}, {"index": 14, "name": "transgirl"}, {"index": 15, "name": "transmisogyny"}, {"index": 16, "name": "gender binary"}, {"index": 17, "name": "dysphoria"}, {"index": 18, "name": "transgender"}, {"index": 19, "name": "transgenders"}, {"index": 20, "name": "voice"}, {"index": 21, "name": "genderfluid"}, {"index": 22, "name": "cishet"}, {"index": 23, "name": "sex-change"}, {"index": 24, "name": "#tgirl"}, {"index": 25, "name": "ladyboy"}, {"index": 26, "name": "afab"}, {"index": 27, "name": "trans-boy"}, {"index": 28, "name": "female-to-male"}, {"index": 29, "name": "trans person of color"}, {"index": 30, "name": "amab"}, {"index": 31, "name": "hormone replacement therapy"}, {"index": 32, "name": "trans-male"}, {"index": 33, "name": "transman"}, {"index": 34, "name": "camab"}, {"index": 35, "name": "binarism"}, {"index": 36, "name": "transgendered"}, {"index": 37, "name": "trans*"}, {"index": 38, "name": "post-op"}, {"index": 39, "name": "transsexual"}, {"index": 40, "name": "third gender"}, {"index": 41, "name": "trans-man"}, {"index": 42, "name": "trans youth"}, {"index": 43, "name": "genderbend"}, {"index": 44, "name": "cisnormativity"}, {"index": 45, "name": "present"}, {"index": 46, "name": "misgender"}, {"index": 47, "name": "transpeople"}, {"index": 48, "name": "gender reassignment"}, {"index": 49, "name": "transwoman"}, {"index": 50, "name": "trans-masculine"}]}